LICENSE
MANIFEST.in
README.md
requirements.txt
setup.py
tox.ini
django_viewclass_mixins.egg-info/PKG-INFO
django_viewclass_mixins.egg-info/SOURCES.txt
django_viewclass_mixins.egg-info/dependency_links.txt
django_viewclass_mixins.egg-info/requires.txt
django_viewclass_mixins.egg-info/top_level.txt
docs/DeactivateMixin.md
docs/FilteredListMixin.md
docs/ObjectOwnerMixin.md
viewclass_mixins/__init__.py
viewclass_mixins/views.py