Metadata-Version: 1.1
Name: django-viewclass-mixins
Version: 1.0
Summary: Helpful mixins for Django View classes.
Home-page: https://bitbucket.org/nextscreenlabs/django-viewclass-mixins
Author: Jason Christa
Author-email: jason@zeitcode.com
License: UNKNOWN
Platform: UNKNOWN
Classifier: Environment :: Web Environment
Classifier: License :: OSI Approved :: BSD License
Classifier: Framework :: Django
Classifier: Programming Language :: Python
